{
  "name": "placement2d_prisa_vpr8",
  "problem_type": "placement2d",
  "evaluation_mode": "placement_only",
  "mode": "placement2d_fixed_ii",
  "result_group": "placement2d/paper_comparison/prisa_vpr8",
  "mapping_bin": "/home/ubuntu/elastic_cgra_mapper/build/mapping",
  "benchmark_sets": [
    {
      "name": "vpr8_normalized",
      "benchmark_root": "/home/ubuntu/elastic_cgra_mapper/benchmark/literature/prisa_vpr8_normalized/vpr8",
      "benchmarks": [
        "motion_vec",
        "fir1",
        "fir2",
        "k4n4op",
        "h2v2_smo",
        "fir16",
        "cosine2",
        "interpolate",
        "w_bmp_head",
        "diffeq2",
        "boundtop",
        "mksmadapter",
        "invert_matrix",
        "blob_merge"
      ]
    }
  ],
  "architectures": [
    {
      "name": "min_square_all_io",
      "template": "/home/ubuntu/elastic_cgra_mapper/research/configs/arch_templates/mesh_10x10_default.json",
      "auto_grid": {
        "policy": "ceil_sqrt_nodes"
      },
      "memory_io": "all",
      "network_type": "orthogonal",
      "ii": 1
    }
  ],
  "mappers": [
    {
      "name": "vpr_sa_fast",
      "runner": "vpr",
      "vpr_bin": "${VPR_BIN:-third_party/vtr/build/vpr/vpr}",
      "arch_xml": "${VPR_ARCH_XML:-third_party/vtr/vtr_flow/arch/timing/k6_N10_40nm.xml}",
      "pack_capacity": 1,
      "vpr_args": [
        "--pack",
        "--place",
        "--absorb_buffer_luts",
        "off",
        "--place_algorithm",
        "bounding_box",
        "--inner_num",
        "0.1",
        "--timing_analysis",
        "off",
        "--const_gen_inference",
        "none",
        "--constant_net_method",
        "route",
        "--sweep_dangling_primary_ios",
        "off",
        "--sweep_dangling_nets",
        "off",
        "--sweep_dangling_blocks",
        "off",
        "--sweep_constant_primary_outputs",
        "off",
        "--disp",
        "off"
      ],
      "allow_missing": true
    },
    {
      "name": "vpr_sa",
      "runner": "vpr",
      "vpr_bin": "${VPR_BIN:-third_party/vtr/build/vpr/vpr}",
      "arch_xml": "${VPR_ARCH_XML:-third_party/vtr/vtr_flow/arch/timing/k6_N10_40nm.xml}",
      "pack_capacity": 1,
      "place_algorithm": "bounding_box",
      "place_all_ops": true,
      "allow_missing": true
    },
    {
      "name": "cpu_mapping_yoto_1000",
      "mapper_config": "/home/ubuntu/elastic_cgra_mapper/research/configs/mapper/placement2d/placement2d_cpu_mapping_yoto_1000_trials_mapper.json"
    },
    {
      "name": "cpu_mapping_yott_1000",
      "mapper_config": "/home/ubuntu/elastic_cgra_mapper/research/configs/mapper/placement2d/placement2d_cpu_mapping_yott_1000_trials_mapper.json"
    },
    {
      "name": "prisa_no_sis",
      "mapper_config": "/home/ubuntu/elastic_cgra_mapper/research/configs/mapper/placement2d/paper_comparison/placement2d_array_prisa_no_sis_mapper.json"
    },
    {
      "name": "prisa",
      "mapper_config": "/home/ubuntu/elastic_cgra_mapper/research/configs/mapper/placement2d/paper_comparison/placement2d_array_prisa_mapper.json"
    }
  ],
  "timeout_sec": 300,
  "parallel_num": 1,
  "mii_missing_distance_policy": "self_loop"
}
